app/__init__.py
app/auth.py
app/config.py
app/db.py
app/main.py
app/models.py
app/s3_service.py
app/owner_meals/__init__.py
app/owner_meals/auth.py
app/owner_meals/restaurant.py
app/owner_meals/router.py
app/owner_meals/schemas.py
app/owner_meals/service.py
vibedish_api-1.0.0.dist-info/METADATA
vibedish_api-1.0.0.dist-info/WHEEL
vibedish_api-1.0.0.dist-info/top_level.txt
vibedish_api-1.0.0.dist-info/RECORD
