Metadata-Version: 2.4
Name: vibedish-api
Version: 1.0.0
Summary: VibeDish - Mood-based food delivery API
Home-page: https://github.com/pranshavpatel/CSC510-Section2-Group8
Author: Pranshav Patel
Requires-Python: >=3.10
Requires-Dist: fastapi==0.120.4
Requires-Dist: uvicorn==0.38.0
Requires-Dist: pydantic==2.12.3
Requires-Dist: pydantic_settings==2.11.0
Requires-Dist: python-dotenv==1.2.1
Requires-Dist: SQLAlchemy==2.0.25
Requires-Dist: alembic==1.17.1
Requires-Dist: asyncpg==0.30.0
Requires-Dist: databases==0.9.0
Requires-Dist: httpx==0.28.1
Requires-Dist: requests==2.32.5
Requires-Dist: boto3==1.35.0
Requires-Dist: python-jose[cryptography]==3.3.0
Requires-Dist: spotipy==2.24.0
Requires-Dist: groq==0.13.0
Requires-Dist: numpy==1.26.4
Requires-Dist: pytest==8.4.2
Requires-Dist: pytest-asyncio==0.24.0
Requires-Dist: pytest-mock==3.14.0
Requires-Dist: pytest-cov==7.0.0
Requires-Dist: pytest-respx==0.22.0
Requires-Dist: pytest-langsmith==0.4.25
Requires-Dist: pytest-anyio==4.10.0
Requires-Dist: psutil==5.9.8
Requires-Dist: memory-profiler==0.61.0
Dynamic: author
Dynamic: home-page
Dynamic: requires-dist
Dynamic: requires-python
Dynamic: summary
